{"nodes": [{"id": "c_scripting_cellpy_docs_contributing_developers_guide_dev_conda_package_md", "label": "dev_conda_package.md", "file_type": "document", "source_file": "C:\\scripting\\cellpy\\docs\\contributing\\developers_guide\\dev_conda_package.md", "source_location": "L1"}, {"id": "developers_guide_dev_conda_package_create_conda_package", "label": "Create conda package", "file_type": "document", "source_file": "C:\\scripting\\cellpy\\docs\\contributing\\developers_guide\\dev_conda_package.md", "source_location": "L1"}, {"id": "developers_guide_dev_conda_package_fork", "label": "Fork", "file_type": "document", "source_file": "C:\\scripting\\cellpy\\docs\\contributing\\developers_guide\\dev_conda_package.md", "source_location": "L5"}, {"id": "developers_guide_dev_conda_package_clone", "label": "Clone", "file_type": "document", "source_file": "C:\\scripting\\cellpy\\docs\\contributing\\developers_guide\\dev_conda_package.md", "source_location": "L10"}, {"id": "developers_guide_dev_conda_package_codeblock_1", "label": "code:shell (git clone https://github.com/your-name/cellpy-feedstok.git)", "file_type": "document", "source_file": "C:\\scripting\\cellpy\\docs\\contributing\\developers_guide\\dev_conda_package.md", "source_location": "L14"}, {"id": "developers_guide_dev_conda_package_get_recent_changes", "label": "Get recent changes", "file_type": "document", "source_file": "C:\\scripting\\cellpy\\docs\\contributing\\developers_guide\\dev_conda_package.md", "source_location": "L19"}, {"id": "developers_guide_dev_conda_package_codeblock_2", "label": "code:shell (git fetch upstream)", "file_type": "document", "source_file": "C:\\scripting\\cellpy\\docs\\contributing\\developers_guide\\dev_conda_package.md", "source_location": "L21"}, {"id": "developers_guide_dev_conda_package_make_a_new_branch_in_your_local_clone", "label": "Make a new branch in your local clone", "file_type": "document", "source_file": "C:\\scripting\\cellpy\\docs\\contributing\\developers_guide\\dev_conda_package.md", "source_location": "L29"}, {"id": "developers_guide_dev_conda_package_codeblock_3", "label": "code:shell (git checkout -b update_x_x_x)", "file_type": "document", "source_file": "C:\\scripting\\cellpy\\docs\\contributing\\developers_guide\\dev_conda_package.md", "source_location": "L31"}, {"id": "developers_guide_dev_conda_package_edit", "label": "Edit", "file_type": "document", "source_file": "C:\\scripting\\cellpy\\docs\\contributing\\developers_guide\\dev_conda_package.md", "source_location": "L34"}, {"id": "developers_guide_dev_conda_package_add_and_commit", "label": "Add and commit", "file_type": "document", "source_file": "C:\\scripting\\cellpy\\docs\\contributing\\developers_guide\\dev_conda_package.md", "source_location": "L39"}, {"id": "developers_guide_dev_conda_package_push", "label": "Push", "file_type": "document", "source_file": "C:\\scripting\\cellpy\\docs\\contributing\\developers_guide\\dev_conda_package.md", "source_location": "L43"}, {"id": "developers_guide_dev_conda_package_codeblock_4", "label": "code:shell (git push origin <branch-name>)", "file_type": "document", "source_file": "C:\\scripting\\cellpy\\docs\\contributing\\developers_guide\\dev_conda_package.md", "source_location": "L45"}, {"id": "developers_guide_dev_conda_package_re_render_if_needed", "label": "Re-render if needed", "file_type": "document", "source_file": "C:\\scripting\\cellpy\\docs\\contributing\\developers_guide\\dev_conda_package.md", "source_location": "L48"}, {"id": "developers_guide_dev_conda_package_codeblock_5", "label": "code:shell (conda install -c conda-forge conda-smithy)", "file_type": "document", "source_file": "C:\\scripting\\cellpy\\docs\\contributing\\developers_guide\\dev_conda_package.md", "source_location": "L53"}, {"id": "developers_guide_dev_conda_package_pull_request_and_merge", "label": "Pull request and merge", "file_type": "document", "source_file": "C:\\scripting\\cellpy\\docs\\contributing\\developers_guide\\dev_conda_package.md", "source_location": "L60"}, {"id": "developers_guide_dev_conda_package_wrap_up", "label": "Wrap up", "file_type": "document", "source_file": "C:\\scripting\\cellpy\\docs\\contributing\\developers_guide\\dev_conda_package.md", "source_location": "L68"}, {"id": "developers_guide_dev_conda_package_codeblock_6", "label": "code:shell (conda search -f cellpy)", "file_type": "document", "source_file": "C:\\scripting\\cellpy\\docs\\contributing\\developers_guide\\dev_conda_package.md", "source_location": "L72"}], "edges": [{"source": "c_scripting_cellpy_docs_contributing_developers_guide_dev_conda_package_md", "target": "developers_guide_dev_conda_package_create_conda_package", "relation": "contains", "confidence": "EXTRACTED", "source_file": "C:\\scripting\\cellpy\\docs\\contributing\\developers_guide\\dev_conda_package.md", "source_location": "L1", "weight": 1.0}, {"source": "developers_guide_dev_conda_package_create_conda_package", "target": "developers_guide_dev_conda_package_fork", "relation": "contains", "confidence": "EXTRACTED", "source_file": "C:\\scripting\\cellpy\\docs\\contributing\\developers_guide\\dev_conda_package.md", "source_location": "L5", "weight": 1.0}, {"source": "developers_guide_dev_conda_package_create_conda_package", "target": "developers_guide_dev_conda_package_clone", "relation": "contains", "confidence": "EXTRACTED", "source_file": "C:\\scripting\\cellpy\\docs\\contributing\\developers_guide\\dev_conda_package.md", "source_location": "L10", "weight": 1.0}, {"source": "developers_guide_dev_conda_package_clone", "target": "developers_guide_dev_conda_package_codeblock_1", "relation": "contains", "confidence": "EXTRACTED", "source_file": "C:\\scripting\\cellpy\\docs\\contributing\\developers_guide\\dev_conda_package.md", "source_location": "L14", "weight": 1.0}, {"source": "developers_guide_dev_conda_package_create_conda_package", "target": "developers_guide_dev_conda_package_get_recent_changes", "relation": "contains", "confidence": "EXTRACTED", "source_file": "C:\\scripting\\cellpy\\docs\\contributing\\developers_guide\\dev_conda_package.md", "source_location": "L19", "weight": 1.0}, {"source": "developers_guide_dev_conda_package_get_recent_changes", "target": "developers_guide_dev_conda_package_codeblock_2", "relation": "contains", "confidence": "EXTRACTED", "source_file": "C:\\scripting\\cellpy\\docs\\contributing\\developers_guide\\dev_conda_package.md", "source_location": "L21", "weight": 1.0}, {"source": "developers_guide_dev_conda_package_create_conda_package", "target": "developers_guide_dev_conda_package_make_a_new_branch_in_your_local_clone", "relation": "contains", "confidence": "EXTRACTED", "source_file": "C:\\scripting\\cellpy\\docs\\contributing\\developers_guide\\dev_conda_package.md", "source_location": "L29", "weight": 1.0}, {"source": "developers_guide_dev_conda_package_make_a_new_branch_in_your_local_clone", "target": "developers_guide_dev_conda_package_codeblock_3", "relation": "contains", "confidence": "EXTRACTED", "source_file": "C:\\scripting\\cellpy\\docs\\contributing\\developers_guide\\dev_conda_package.md", "source_location": "L31", "weight": 1.0}, {"source": "developers_guide_dev_conda_package_create_conda_package", "target": "developers_guide_dev_conda_package_edit", "relation": "contains", "confidence": "EXTRACTED", "source_file": "C:\\scripting\\cellpy\\docs\\contributing\\developers_guide\\dev_conda_package.md", "source_location": "L34", "weight": 1.0}, {"source": "developers_guide_dev_conda_package_create_conda_package", "target": "developers_guide_dev_conda_package_add_and_commit", "relation": "contains", "confidence": "EXTRACTED", "source_file": "C:\\scripting\\cellpy\\docs\\contributing\\developers_guide\\dev_conda_package.md", "source_location": "L39", "weight": 1.0}, {"source": "developers_guide_dev_conda_package_create_conda_package", "target": "developers_guide_dev_conda_package_push", "relation": "contains", "confidence": "EXTRACTED", "source_file": "C:\\scripting\\cellpy\\docs\\contributing\\developers_guide\\dev_conda_package.md", "source_location": "L43", "weight": 1.0}, {"source": "developers_guide_dev_conda_package_push", "target": "developers_guide_dev_conda_package_codeblock_4", "relation": "contains", "confidence": "EXTRACTED", "source_file": "C:\\scripting\\cellpy\\docs\\contributing\\developers_guide\\dev_conda_package.md", "source_location": "L45", "weight": 1.0}, {"source": "developers_guide_dev_conda_package_create_conda_package", "target": "developers_guide_dev_conda_package_re_render_if_needed", "relation": "contains", "confidence": "EXTRACTED", "source_file": "C:\\scripting\\cellpy\\docs\\contributing\\developers_guide\\dev_conda_package.md", "source_location": "L48", "weight": 1.0}, {"source": "developers_guide_dev_conda_package_re_render_if_needed", "target": "developers_guide_dev_conda_package_codeblock_5", "relation": "contains", "confidence": "EXTRACTED", "source_file": "C:\\scripting\\cellpy\\docs\\contributing\\developers_guide\\dev_conda_package.md", "source_location": "L53", "weight": 1.0}, {"source": "developers_guide_dev_conda_package_create_conda_package", "target": "developers_guide_dev_conda_package_pull_request_and_merge", "relation": "contains", "confidence": "EXTRACTED", "source_file": "C:\\scripting\\cellpy\\docs\\contributing\\developers_guide\\dev_conda_package.md", "source_location": "L60", "weight": 1.0}, {"source": "developers_guide_dev_conda_package_create_conda_package", "target": "developers_guide_dev_conda_package_wrap_up", "relation": "contains", "confidence": "EXTRACTED", "source_file": "C:\\scripting\\cellpy\\docs\\contributing\\developers_guide\\dev_conda_package.md", "source_location": "L68", "weight": 1.0}, {"source": "developers_guide_dev_conda_package_wrap_up", "target": "developers_guide_dev_conda_package_codeblock_6", "relation": "contains", "confidence": "EXTRACTED", "source_file": "C:\\scripting\\cellpy\\docs\\contributing\\developers_guide\\dev_conda_package.md", "source_location": "L72", "weight": 1.0}], "input_tokens": 0, "output_tokens": 0}